plugin.cmake
setup.py
girder_candela/__init__.py
girder_candela.egg-info/PKG-INFO
girder_candela.egg-info/SOURCES.txt
girder_candela.egg-info/dependency_links.txt
girder_candela.egg-info/entry_points.txt
girder_candela.egg-info/not-zip-safe
girder_candela.egg-info/requires.txt
girder_candela.egg-info/top_level.txt
girder_candela/web_client/main.js
girder_candela/web_client/package.json
girder_candela/web_client/webpack.helper.js
girder_candela/web_client/stylesheets/candelaParameters.styl
girder_candela/web_client/stylesheets/candelaWidget.styl
girder_candela/web_client/templates/candelaParameters.pug
girder_candela/web_client/templates/candelaWidget.pug
girder_candela/web_client/views/CandelaParametersView.js
girder_candela/web_client/views/CandelaWidget.js
girder_candela/web_client/views/ItemView.js
plugin_tests/candelaSpec.js